{
  "machine": "centrifuge_tungstensteel",
  "registryName": "centrifuge_tungstensteel_tier4_centrifuge_sticky_resin",
  "recipeTime": 3,
  "requirements": [
    {
      "type": "energy",
      "io-type": "input",
      "item": null,
      "amount": 0,
      "fluid": null,
      "energyPerTick": 36969,
      "chance": 1.0
    },
    {
      "type": "item",
      "io-type": "input",
      "item": "ore:gearboxTitanium",
      "amount": 1,
      "fluid": null,
      "energyPerTick": 0,
      "chance": 0.0
    },
    {
      "type": "item",
      "io-type": "input",
      "item": "ore:stickyResin",
      "amount": 1,
      "fluid": null,
      "energyPerTick": 0,
      "chance": 1.0
    },
    {
      "type": "item",
      "io-type": "output",
      "item": "ore:dustRawRubber",
      "amount": 2,
      "fluid": null,
      "energyPerTick": 0,
      "chance": 1.0
    },
    {
      "type": "item",
      "io-type": "output",
      "item": "ore:tinyDustRawRubber",
      "amount": 21,
      "fluid": null,
      "energyPerTick": 0,
      "chance": 1.0
    }
  ]
}